ASLPAw_package/ASLPAw_module.py
ASLPAw_package/__init__.py
ASLPAw-2.2.0.dist-info/LICENSE
ASLPAw-2.2.0.dist-info/METADATA
ASLPAw-2.2.0.dist-info/WHEEL
ASLPAw-2.2.0.dist-info/top_level.txt
ASLPAw-2.2.0.dist-info/RECORD
