Metadata-Version: 2.1
Name: ASLPAw
Version: 2.2.0
Summary: Adaptive overlapping community discovery algorithm package in python.
Home-page: https://github.com/fsssosei/ASLPAw
Author: sosei
Author-email: fss.sosei@gmail.com
License: GNU Affero General Public License v3
Keywords: community,LPA
Platform: UNKNOWN
Classifier: Development Status :: 5 - Production/Stable
Classifier: License :: OSI Approved :: GNU Affero General Public License v3
Classifier: Programming Language :: Python :: 3.8
Requires-Python: >=3.8
Requires-Dist: networkx (>=2.4)
Requires-Dist: multivalued-dict (>=2.0.1)
Requires-Dist: shuffle-graph (>=2.2.0)
Requires-Dist: count-dict (>=1.1.1)
Requires-Dist: similarity-index-of-label-graph (>=2.0.1)
Requires-Dist: scikit-learn (>=0.24.1)
